LICENSE
README.md
setup.py
flask_request_id/__init__.py
flask_request_id/log.py
flask_request_id/server.py
flask_request_id/utils.py
flask_request_idx.egg-info/PKG-INFO
flask_request_idx.egg-info/SOURCES.txt
flask_request_idx.egg-info/dependency_links.txt
flask_request_idx.egg-info/requires.txt
flask_request_idx.egg-info/top_level.txt
flask_request_idx.egg-info/zip-safe