Metadata-Version: 2.1
Name: flask-request-idx
Version: 0.0.1
Summary: Python Framework.
Home-page: UNKNOWN
Author: mfkifhss
Author-email: mfkifhss@gmail.com
License: MIT
Platform: any
Classifier: Programming Language :: Python :: 3
Classifier: License :: OSI Approved :: MIT License
Classifier: Operating System :: OS Independent
License-File: LICENSE
